LICENSE
MANIFEST.in
README.md
README.rst
setup.cfg
setup.py
pyhttpx/__init__.py
pyhttpx/__version__.py
pyhttpx/compat.py
pyhttpx/exception.py
pyhttpx/models.py
pyhttpx/session.py
pyhttpx/utils.py
pyhttpx/websocket.py
pyhttpx.egg-info/PKG-INFO
pyhttpx.egg-info/SOURCES.txt
pyhttpx.egg-info/dependency_links.txt
pyhttpx.egg-info/not-zip-safe
pyhttpx.egg-info/requires.txt
pyhttpx.egg-info/top_level.txt
pyhttpx/layers/__init__.py
pyhttpx/layers/tls/__init__.py
pyhttpx/layers/tls/extensions.py
pyhttpx/layers/tls/fields.py
pyhttpx/layers/tls/handshake.py
pyhttpx/layers/tls/keyexchange.py
pyhttpx/layers/tls/pyaiossl.py
pyhttpx/layers/tls/pysocks.py
pyhttpx/layers/tls/pyssl.py
pyhttpx/layers/tls/suites.py
pyhttpx/layers/tls/tls_context.py
pyhttpx/layers/tls/crypto/__init__.py
pyhttpx/layers/tls/crypto/aes.py
pyhttpx/layers/tls/crypto/chacha20_poly1305.py
pyhttpx/layers/tls/crypto/cipher_aead.py
pyhttpx/layers/tls/crypto/cipher_block.py
pyhttpx/layers/tls/crypto/ciphers.py
pyhttpx/layers/tls/crypto/ecc.py
pyhttpx/layers/tls/crypto/hkdf.py
pyhttpx/layers/tls/crypto/kx_algs.py
pyhttpx/layers/tls/crypto/prf.py
pyhttpx/layers/tls/linux/__init__.py
pyhttpx/layers/tls/window/__init__.py
tests/__init__.py
tests/requestTest.py
tests/websocketTest.py