Metadata-Version: 1.0
Name: pyhttpx
Version: 2.10.12
Summary: HTTP library.
Home-page: https://github.com/zero3301/pyhttpx
Author: 3301
Author-email: 1114135928@qq.com
License: MIT Licence
Keywords: pip,pyhttpx
Platform: any
